precompressed/templatetags
precompressed
precompressed/storage
