Metadata-Version: 1.0
Name: django-precompressed
Version: 0.0.2
Summary: precompressed is a pluggable application for Django developers who want to serve precompressed (gzipped) static files.
Home-page: https://github.com/jhmaddox/django-precompressed/
Author: James Maddox
Author-email: jhmaddox@gmail.com
License: BSD
Platform: UNKNOWN
